starmerx_apollo_client/__init__.py
starmerx_apollo_client/apollo_client.py
starmerx_apollo_client/base.py
starmerx_apollo_client/util.py
starmerx_apollo_client/Demo/__init__.py
starmerx_apollo_client/Demo/get_value_using_client.py
starmerx_apollo_client/Demo/start_client_with_logger.py
starmerx_apollo_client/Demo/start_client_without_hot_update.py
starmerx_apollo_client-0.0.8.dist-info/LICENSE
starmerx_apollo_client-0.0.8.dist-info/METADATA
starmerx_apollo_client-0.0.8.dist-info/WHEEL
starmerx_apollo_client-0.0.8.dist-info/top_level.txt
starmerx_apollo_client-0.0.8.dist-info/RECORD
