Metadata-Version: 2.1
Name: starmerx-apollo-client
Version: 0.0.8
Summary: starmerx apollo client
Author: Wilson
Author-email: chengwenxian@starmerx.com
License: UNKNOWN
Platform: UNKNOWN
Classifier: Programming Language :: Python :: 3
Classifier: License :: OSI Approved :: MIT License
Classifier: Operating System :: OS Independent
Requires-Python: >=3.5
License-File: LICENSE
Requires-Dist: urllib3 (>=1.25.2)
Requires-Dist: requests (>=2.22.0)
